databricks_stage.py
databricks_stage-1.0.15.dist-info/LICENSE
databricks_stage-1.0.15.dist-info/METADATA
databricks_stage-1.0.15.dist-info/WHEEL
databricks_stage-1.0.15.dist-info/entry_points.txt
databricks_stage-1.0.15.dist-info/top_level.txt
databricks_stage-1.0.15.dist-info/RECORD
