Metadata-Version: 2.1
Name: databricks-stage
Version: 1.0.15
Summary: Stages data to specified blob storage container
Author: Sisu Data Inc.
License: Copyright 2022 Sisu Data Inc.        
Classifier: License :: OSI Approved :: MIT License
Classifier: Programming Language :: Python
Classifier: Programming Language :: Python :: 3
Requires-Python: >=3.6
License-File: LICENSE
Requires-Dist: pyspark
